{
  "marketing_stripe": {
    "text": "",
    "link": ""
  },
  "contacts_stripe": {
    "pages": [
      {
        "link": "contato@fitpop.com.br "
      },
      {
        "title": "Atendimento",
        "link": "https://www.fitpop.com.br/contato"
      },
      {
        "title": "Compras",
        "link": "https://www.fitpop.com.br/carrinho"
      },
      {
        "title": "Meus Favoritos",
        "link": "https://www.fitpop.com.br/favoritos"
      }
    ],
    "phone_wpp": true,
    "socials": true
  },
  "categories_list": {
    "featured": [
      "/conjuntos?CONJUNTOS",
      "/leggings?LEGGINGS",
      "/top?TOP"
    ],
    "random": 0,
    "full_width": true
  },
  "search_input": true
}